{
  "week": 9,
  "days": [
    [
      {
        "day": 1,
        "book": "NUM",
        "chapters": {
          "start": {
            "number": 7
          },
          "end": {
            "number": 7
          }
        }
      }
    ],
    [
      {
        "day": 2,
        "book": "NUM",
        "chapters": {
          "start": {
            "number": 8
          },
          "end": {
            "number": 10
          }
        }
      }
    ],
    [
      {
        "day": 3,
        "book": "NUM",
        "chapters": {
          "start": {
            "number": 11
          },
          "end": {
            "number": 13
          }
        }
      }
    ],
    [
      {
        "day": 4,
        "book": "NUM",
        "chapters": {
          "start": {
            "number": 14
          },
          "end": {
            "number": 15
          }
        }
      },
      {
        "day": 4,
        "book": "PSA",
        "chapters": {
          "start": {
            "number": 90
          },
          "end": {
            "number": 90
          }
        }
      }
    ],
    [
      {
        "day": 5,
        "book": "NUM",
        "chapters": {
          "start": {
            "number": 18
          },
          "end": {
            "number": 20
          }
        }
      }
    ],
    [
      {
        "day": 6,
        "book": "NUM",
        "chapters": {
          "start": {
            "number": 21
          },
          "end": {
            "number": 22
          }
        }
      }
    ]
  ]
}